microterm/__init__.py
microterm/__main__.py
microterm-0.1.0.dist-info/LICENSE
microterm-0.1.0.dist-info/METADATA
microterm-0.1.0.dist-info/WHEEL
microterm-0.1.0.dist-info/top_level.txt
microterm-0.1.0.dist-info/RECORD
