Metadata-Version: 2.1
Name: microterm
Version: 0.1.0
Summary: CLI tool for interacting with MicroPython devices
Home-page: https://github.com/wybiral/microterm
Author: davy wybiral
Author-email: davy.wybiral@gmail.com
License: MIT
Classifier: Programming Language :: Python :: 3
Classifier: License :: OSI Approved :: MIT License
Classifier: Operating System :: OS Independent
License-File: LICENSE
Requires-Dist: pyserial
